ds20kdb/__init__.py
ds20kdb/auth.py
ds20kdb/default.py
ds20kdb/request.py
ds20kdb-0.0.6.dist-info/METADATA
ds20kdb-0.0.6.dist-info/WHEEL
ds20kdb-0.0.6.dist-info/top_level.txt
ds20kdb-0.0.6.dist-info/RECORD
